{"nodes": [{"id": "20260518_thesis_report", "label": "Thesis Report: Hybrid Stacking XAU/USD (20260518 session)", "file_type": "document", "source_file": "results/XAUUSD_1H_20260518_182200/reports/thesis_report.md", "source_location": null, "source_url": null, "captured_at": null, "author": null, "contributor": null}, {"id": "20260518_backtest_demo", "label": "Backtest Demo: +11.57% return, MaxDD 4.03%, 275 trades, PF 1.28", "file_type": "document", "source_file": "results/XAUUSD_1H_20260518_182200/reports/thesis_report.md", "source_location": null, "source_url": null, "captured_at": null, "author": null, "contributor": null}], "edges": [{"source": "20260518_thesis_report", "target": "20260518_model_eval", "relation": "references", "confidence": "EXTRACTED", "confidence_score": 0.95, "source_file": "results/XAUUSD_1H_20260518_182200/reports/thesis_report.md", "source_location": null, "weight": 1.0}, {"source": "20260518_thesis_report", "target": "20260518_backtest_demo", "relation": "references", "confidence": "EXTRACTED", "confidence_score": 0.95, "source_file": "results/XAUUSD_1H_20260518_182200/reports/thesis_report.md", "source_location": null, "weight": 1.0}], "hyperedges": [{"id": "20260518_result_package", "label": "20260518 Session Result Package", "nodes": ["20260518_thesis_report", "20260518_model_eval", "20260518_backtest_demo"], "relation": "form", "confidence": "EXTRACTED", "confidence_score": 0.95, "source_file": "results/XAUUSD_1H_20260518_182200/reports/thesis_report.md"}]}