{"nodes": [{"id": "htmlcov_build_labels_py", "label": "Coverage Report: dataset/build_labels.py", "file_type": "document", "source_file": "htmlcov/z_c2539c59a2404d5b_build_labels_py.html", "source_location": null, "source_url": null, "captured_at": null, "author": null, "contributor": null}], "edges": [{"source": "htmlcov_build_labels_py", "target": "htmlcov_dataset_label_numba_py", "relation": "references", "confidence": "INFERRED", "confidence_score": 0.8, "source_file": "htmlcov/z_c2539c59a2404d5b_build_labels_py.html", "source_location": null, "weight": 0.8}, {"source": "htmlcov_build_labels_py", "target": "htmlcov_stage3_label_numba_py", "relation": "references", "confidence": "INFERRED", "confidence_score": 0.8, "source_file": "htmlcov/z_c2539c59a2404d5b_build_labels_py.html", "source_location": null, "weight": 0.8}], "hyperedges": []}